ag_ui_crewai/__init__.py
ag_ui_crewai/context.py
ag_ui_crewai/crews.py
ag_ui_crewai/endpoint.py
ag_ui_crewai/enterprise.py
ag_ui_crewai/events.py
ag_ui_crewai/sdk.py
ag_ui_crewai/utils.py
ag_ui_crewai-0.1.5.dist-info/METADATA
ag_ui_crewai-0.1.5.dist-info/WHEEL
ag_ui_crewai-0.1.5.dist-info/entry_points.txt
ag_ui_crewai-0.1.5.dist-info/RECORD
